tool.py
famokuai/__init__.py
famokuai/text.py
famokuai/zelibone.py
famokuai-1.0.0.dist-info/LICENSE.txt
famokuai-1.0.0.dist-info/METADATA
famokuai-1.0.0.dist-info/WHEEL
famokuai-1.0.0.dist-info/top_level.txt
famokuai-1.0.0.dist-info/RECORD
