Metadata-Version: 2.1
Name: famokuai
Version: 1.0.0
Summary: this is a niubi lib
Author: lizhi
Author-email: 1249705133@qq.com
License: MIT
License-File: LICENSE.txt
